[{"Id":41,"OrderIndex":1,"ClassMask":128},{"Id":61,"OrderIndex":2,"ClassMask":128},{"Id":81,"OrderIndex":0,"ClassMask":128},{"Id":161,"OrderIndex":0,"ClassMask":1},{"Id":163,"OrderIndex":2,"ClassMask":1},{"Id":164,"OrderIndex":1,"ClassMask":1},{"Id":181,"OrderIndex":1,"ClassMask":8},{"Id":182,"OrderIndex":0,"ClassMask":8},{"Id":183,"OrderIndex":2,"ClassMask":8},{"Id":201,"OrderIndex":0,"ClassMask":16},{"Id":202,"OrderIndex":1,"ClassMask":16},{"Id":203,"OrderIndex":2,"ClassMask":16},{"Id":261,"OrderIndex":0,"ClassMask":64},{"Id":262,"OrderIndex":2,"ClassMask":64},{"Id":263,"OrderIndex":1,"ClassMask":64},{"Id":281,"OrderIndex":1,"ClassMask":1024},{"Id":282,"OrderIndex":2,"ClassMask":1024},{"Id":283,"OrderIndex":0,"ClassMask":1024},{"Id":301,"OrderIndex":2,"ClassMask":256},{"Id":302,"OrderIndex":0,"ClassMask":256},{"Id":303,"OrderIndex":1,"ClassMask":256},{"Id":361,"OrderIndex":0,"ClassMask":4},{"Id":362,"OrderIndex":2,"ClassMask":4},{"Id":363,"OrderIndex":1,"ClassMask":4},{"Id":381,"OrderIndex":2,"ClassMask":2},{"Id":382,"OrderIndex":0,"ClassMask":2},{"Id":383,"OrderIndex":1,"ClassMask":2}]