{"flightmaster":[{"coords":[[78.4,50.2]],"level":0,"name":"Skymaster Baeric","type":1,"id":30269,"reacthorde":1,"reactalliance":-1,"description":"Dragonhawk Master"},{"coords":[[72.0,80.8]],"level":0,"name":"Galendror Whitewing","type":1,"id":30271,"reacthorde":-1,"reactalliance":1,"description":"Hippogryph Master"}],"innkeeper":null,"repair":[{"coords":[[74.6,79.4]],"level":0,"name":"Lanudal Silverhart","type":1,"id":30241,"reacthorde":-1,"reactalliance":1,"description":"Blacksmithing Supplies"},{"coords":[[77.8,49.8]],"level":0,"name":"Felindel Sunhammer","type":1,"id":30253,"reacthorde":1,"reactalliance":-1,"description":"Blacksmithing Supplies"}],"vendor":[{"coords":[[78.2,50.0]],"level":0,"name":"Alanura Firecloud","type":1,"id":30239,"reacthorde":1,"reactalliance":-1,"description":"Poisons & Reagents"},{"coords":[[74.6,79.4]],"level":0,"name":"Lanudal Silverhart","type":1,"id":30241,"reacthorde":-1,"reactalliance":1,"description":"Blacksmithing Supplies"},{"coords":[[75.0,78.8]],"level":0,"name":"Miura Brightweaver","type":1,"id":30244,"reacthorde":-1,"reactalliance":1,"description":"Poisons & Reagents"},{"coords":[[77.8,49.8]],"level":0,"name":"Felindel Sunhammer","type":1,"id":30253,"reacthorde":1,"reactalliance":-1,"description":"Blacksmithing Supplies"},{"coords":[[78.6,48.4]],"level":0,"name":"Marisalira","type":1,"id":30254,"reacthorde":1,"reactalliance":-1,"description":"Food & Drink"},{"coords":[[74.6,79.0]],"level":0,"name":"Aniduria","type":1,"id":30255,"reacthorde":-1,"reactalliance":1,"description":"Food & Drink"},{"coords":[[77.4,49.6]],"level":0,"name":"Scout Ordimbral","type":1,"id":30256,"reacthorde":1,"reactalliance":-1,"description":"General Goods"},{"coords":[[74.2,79.6]],"level":0,"name":"Scout Yribria","type":1,"id":30257,"reacthorde":0,"reactalliance":1,"description":"General Goods"},{"coords":[[34.0,35.6]],"level":0,"name":"Kaye Toogie","type":1,"id":35826,"reacthorde":1,"reactalliance":1,"description":null}],"trainer":null,"herb":{"Crystalsong Carrot":[{"coords":[[25.4,40.4],[25.4,40.5],[25.7,40.4],[25.9,39.3],[26.3,40.7],[26.3,41.6],[26.4,46.7],[26.5,41.8],[26.8,45.4],[27.0,45.5],[27.1,41.0],[27.3,39.4],[27.3,39.5],[27.3,47.1],[27.4,37.2],[27.4,43.4],[27.5,37.3],[27.5,39.5],[27.7,43.4],[27.7,43.5],[27.9,45.4],[28.0,37.5],[28.0,38.6],[28.0,45.7],[28.2,41.4],[28.2,46.6],[28.3,41.7],[28.4,47.6],[28.5,47.4],[28.5,47.5],[28.7,42.4],[28.7,42.5],[28.8,37.8],[28.8,45.4],[28.8,45.5],[29.1,38.8],[29.4,37.0],[29.5,36.9],[29.7,42.1],[29.9,40.5],[30.1,38.9],[30.1,40.3],[30.2,43.6],[30.3,38.2],[30.4,42.7],[30.5,37.0],[30.5,38.2],[30.5,43.7],[30.9,42.5],[31.0,42.4],[31.1,40.5],[31.2,40.2],[31.4,38.5],[31.5,38.4],[31.5,38.5],[31.5,43.3],[31.7,43.9],[32.0,42.4],[32.4,41.1],[32.5,41.1]],"level":0,"name":"Crystalsong Carrot","type":2,"id":192828}],"Winter Hyacinth":[{"coords":[[14.7,15.4],[14.7,15.5],[16.4,13.3],[16.4,13.5],[16.5,13.3],[16.5,13.5],[18.3,15.7],[18.4,15.4],[18.5,15.7],[19.3,12.0],[19.5,11.9],[20.7,10.4],[20.7,10.6],[46.3,36.6],[70.2,76.6],[70.9,75.7],[71.7,76.8],[72.2,75.2],[72.8,74.6]],"level":0,"name":"Winter Hyacinth","type":2,"id":194213}]},"vein":{"Cobalt Deposit":[{"coords":[[10.0,68.6],[28.3,87.8],[29.7,84.9],[29.8,73.5],[29.9,73.3],[58.5,40.9],[93.4,61.4],[93.4,61.5],[93.5,61.4],[93.6,61.6],[96.0,41.2]],"level":0,"name":"Cobalt Deposit","type":2,"id":189978}],"Rich Cobalt Deposit":[{"coords":[[28.3,87.8],[29.9,73.4],[29.9,84.8],[93.4,61.4],[93.4,61.5],[93.5,61.5],[93.6,61.4],[96.1,41.2]],"level":0,"name":"Rich Cobalt Deposit","type":2,"id":189979}],"Saronite Deposit":[{"coords":[[23.8,19.9],[25.1,20.9],[26.4,17.4],[26.4,17.5],[26.6,17.4],[26.6,17.6],[29.8,25.7],[32.4,28.9],[32.5,28.8],[39.1,32.9],[40.7,33.0],[74.7,79.0],[75.3,77.6],[76.7,81.1],[93.4,61.4],[95.9,41.2]],"level":0,"name":"Saronite Deposit","type":2,"id":189980}],"Rich Saronite Deposit":[{"coords":[[23.7,19.9],[25.1,20.9],[26.6,17.4],[26.6,17.6],[29.8,25.8],[32.4,28.9],[32.5,28.7],[39.1,32.9],[40.6,33.0]],"level":0,"name":"Rich Saronite Deposit","type":2,"id":189981}],"Titanium Vein":[{"coords":[[23.7,19.8],[25.1,20.8],[26.6,17.4],[26.6,17.6],[29.8,25.8],[32.4,28.9],[32.5,28.8],[39.0,33.2],[40.7,33.0]],"level":0,"name":"Titanium Vein","type":2,"id":191133}]},"skinnable":[26358,26359,31233,31236,31393,31402,31403,31404],"gatherable":[30861,31229],"minable":[26291,29436],"salvegable":[]}